smady/__init__.py
smady/_version.py
smady/anomaly_detectors.py
smady/climatology.py
smady/data_reader.py
smady/indicators.py
smady/map.py
smady/metadata.py
smady/plot.py
smady/preprocess.py
smady/skeleton.py
smady/utils.py
smady/workflow.py
smady-0.1.0.dist-info/LICENSE.txt
smady-0.1.0.dist-info/METADATA
smady-0.1.0.dist-info/WHEEL
smady-0.1.0.dist-info/top_level.txt
smady-0.1.0.dist-info/RECORD
