Metadata-Version: 2.1
Name: smady
Version: 0.1.0
Summary: Anomaly detection workflow for time series data, mainly for surface soil moisture data.
Home-page: https://github.com/MuhammedM294/smady
Author: MuhammedM294
Author-email: muhammedaabdelaal@gmail.com
License: MIT
Project-URL: Documentation, https://pyscaffold.org/
Platform: any
Classifier: Development Status :: 4 - Beta
Classifier: Programming Language :: Python
License-File: LICENSE.txt
Requires-Dist: importlib-metadata ; python_version < "3.8"
Provides-Extra: testing
Requires-Dist: setuptools ; extra == 'testing'
Requires-Dist: pytest ; extra == 'testing'
Requires-Dist: pytest-cov ; extra == 'testing'
